<entities anm2root="" version="5">
    <entity anm2path="stageapi/none.anm2" id="1000" name="StageAPIBridge" variant="12537" collisionRadius="0" numGridCollisionPoints="0">
        <gibs amount="0" blood="0" bone="0" eye="0" gut="0" large="0" />
    </entity>
    <entity anm2path="stageapi/none.anm2" id="1000" name="StageAPIBackdrop" variant="12538" collisionRadius="0" numGridCollisionPoints="0">
        <gibs amount="0" blood="0" bone="0" eye="0" gut="0" large="0" />
    </entity>
    <entity anm2path="stageapi/none.anm2" id="1000" name="StageAPIShading" variant="12539" collisionRadius="0" numGridCollisionPoints="0">
        <gibs amount="0" blood="0" bone="0" eye="0" gut="0" large="0" />
    </entity>
    <entity anm2path="stageapi/none.anm2" id="1000" name="StageAPIGenericEffect" variant="12544" collisionRadius="0" numGridCollisionPoints="0">
        <gibs amount="0" blood="0" bone="0" eye="0" gut="0" large="0" />
    </entity>
    <entity anm2path="stageapi/none.anm2" id="1000" name="StageAPIFloorEffect" variant="22" subtype="12545" collisionRadius="0" numGridCollisionPoints="0">
        <gibs amount="0" blood="0" bone="0" eye="0" gut="0" large="0" />
    </entity>
    <entity anm2path="stageapi/none.anm2" id="1000" name="StageAPITrapdoor" variant="12546" collisionRadius="0" numGridCollisionPoints="0">
        <gibs amount="0" blood="0" bone="0" eye="0" gut="0" large="0" />
    </entity>
    <entity anm2path="stageapi/none.anm2" id="1000" name="StageAPIDeleteMeEffect" variant="12540" collisionRadius="0" numGridCollisionPoints="0">
        <gibs amount="0" blood="0" bone="0" eye="0" gut="0" large="0" />
    </entity>
    <entity anm2path="stageapi/none.anm2" id="865" name="StageAPIDeleteMeNPC" variant="12541" collisionRadius="1" numGridCollisionPoints="1">
        <gibs amount="0" blood="0" bone="0" eye="0" gut="0" large="0" />
    </entity>
    <entity anm2path="stageapi/none.anm2" id="9" name="StageAPIDeleteMeProjectile" variant="12542" collisionRadius="1" numGridCollisionPoints="1">
        <gibs amount="0" blood="0" bone="0" eye="0" gut="0" large="0" />
    </entity>
    <entity anm2path="stageapi/none.anm2" id="5" name="StageAPIDeleteMePickup" variant="12543" collisionRadius="1" numGridCollisionPoints="1">
        <gibs amount="0" blood="0" bone="0" eye="0" gut="0" large="0" />
    </entity>
</entities>
